pyorcai2c/__init__.py
pyorcai2c/pyorcai2c.py
pyorcai2c/utils.py
pyorcai2c-0.0.12.dist-info/METADATA
pyorcai2c-0.0.12.dist-info/WHEEL
pyorcai2c-0.0.12.dist-info/licenses/LICENSE
pyorcai2c-0.0.12.dist-info/RECORD
