Metadata-Version: 2.3
Name: pyorcai2c
Version: 0.0.12
Summary: python wrapper for I2C communications with ORCASEMI devices through FTDI
Project-URL: Homepage, https://github.com/orcasemi/pyorcai2c
Project-URL: Issues, https://github.com/orcasemi/pyorcai2c/issues
Author-email: cvalgoi <cristian.valgoi@orcasemi.com>
License: This is free and unencumbered software released into the public domain.
Classifier: Operating System :: OS Independent
Classifier: Programming Language :: Python :: 3
Requires-Python: >=3.9
Requires-Dist: ftd2xx==1.3.8
